{"singlePage": [], "startSite": "", "filingNum": "", "onePageListNum": 15, "commentLabelColor": "#006b75", "yearColorList": ["#bc4c00", "#0969da", "#1f883d", "#A333D0"], "i18n": "CN", "themeMode": "manual", "dayTheme": "light", "nightTheme": "dark", "urlMode": "pinyin", "script": "", "style": "", "head": "", "indexScript": "", "indexStyle": "", "bottomText": "", "showPostSource": 1, "iconList": {}, "UTC": 8, "rssSplit": "sentence", "exlink": {}, "needComment": 1, "allHead": "<script src='https://blog.meekdai.com/Gmeek/plugins/GmeekVercount.js'></script><script src='https://blog.meekdai.com/Gmeek/plugins/GmeekTOC.js'></script>", "title": "\u7fbd\u672b\u306e\u81ea\u7559\u5730", "subTitle": "\u65e0\u4e1a\u6e38\u6c11\u7684\u65e5\u5e38\u5439\u6c34\u3002", "avatarUrl": "https://avatars.githubusercontent.com/u/161136026", "email": "yukiend@outlook.com", "GMEEK_VERSION": "last", "postListJson": {"P1": {"htmlDir": "docs/post/ni-hao-\uff0c-shi-jie-\u3002.html", "labels": ["\u65e5\u5e38"], "postTitle": "\u4f60\u597d\uff0c\u4e16\u754c\u3002", "postUrl": "post/ni-hao-%EF%BC%8C-shi-jie-%E3%80%82.html", "postSourceUrl": "https://github.com/LinMoyu233/linmoyu233.github.io/issues/1", "commentNum": 0, "wordCount": 97, "description": "gucraft.cn\u8fc7\u671f\u4e86\uff0c \u76ee\u524d\u65e0\u8d44\u91d1\u800c\u4e14\u4e5f\u4e0d\u662f\u5f88\u6709\u5fc5\u8981ALO\u548c\u57df\u540d\uff0c\u4e89\u53d6\u672a\u6765\u4e24\u4e09\u4e2a\u6708\u641e\u5b8c\uff08\u4e3b\u8981\u662f\u88ab\u513f\u7ae5\u52ab\u4e86\uff0c\u54c8\u54c8\uff09\r\n\u5148\u627e\u4e2a\u5730\u65b9\u628a\u6c34\u6587\u6c34\u4e86\uff0c\u4ee5\u524d\u6709\u8bd5\u8fc7Gridea\u4f46\u662f\u4e2a\u4eba\u61d2\u5f97\u5907\u4efd\u6587\u4ef6\u3002", "top": 0, "createdAt": 1727526609, "style": "", "script": "", "head": "", "ogImage": "https://avatars.githubusercontent.com/u/161136026", "createdDate": "2024-09-28", "dateLabelColor": "#bc4c00"}, "P2": {"htmlDir": "docs/post/Re\uff1a-ji-yi-ci-fu-jian-mou-zhong-zhi-yuan-qu-shang-wang-zhe-teng.html", "labels": ["\u6280\u672f\u8e29\u5751"], "postTitle": "Re\uff1a\u8bb0\u4e00\u6b21\u798f\u5efa\u67d0\u4e2d\u804c\u56ed\u533a\u4e0a\u7f51\u6298\u817e", "postUrl": "post/Re%EF%BC%9A-ji-yi-ci-fu-jian-mou-zhong-zhi-yuan-qu-shang-wang-zhe-teng.html", "postSourceUrl": "https://github.com/LinMoyu233/linmoyu233.github.io/issues/2", "commentNum": 0, "wordCount": 5555, "description": "~~\u526f\uff1a\u8bb0\u4e00\u6b21\u5b81\u6280/\u5b81\u8d22\u7ecf\u4e0a\u7f51\u6298\u817e\u5e76\u62f7\u6253fvv\u4fe1\u606f\u79d1~~\r\n\r\n> [!WARNING]\r\n> **\u514d\u8d23\u8b66\u544a**\r\n> **\u53ef\u4ee5\u901a\u8fc7\u6b64\u6587\u6765\u53cd\u63a8\u505a\u51fa\u4e00\u4e9b\u8fdd\u6cd5\u884c\u4e3a\uff0c\u672c\u4eba\u4e0d\u5bf9\u6240\u505a\u51fa\u8fdd\u6cd5\u884c\u4e3a\u8d1f\u8d23\u3002", "top": 0, "createdAt": 1727529297, "style": "<style>.markdown-alert{padding:0.5rem 1rem;margin-bottom:1rem;border-left:.25em solid var(--borderColor-default,var(--color-border-default));}.markdown-alert .markdown-alert-title {display:flex;font-weight:var(--base-text-weight-medium,500);align-items:center;line-height:1;}.markdown-alert>:first-child {margin-top:0;}.markdown-alert>:last-child {margin-bottom:0;}</style><style>.markdown-alert.markdown-alert-note {border-left-color:var(--borderColor-accent-emphasis, var(--color-accent-emphasis));background-color:var(--color-accent-subtle);}.markdown-alert.markdown-alert-note .markdown-alert-title {color: var(--fgColor-accent,var(--color-accent-fg));}</style><style>.markdown-alert.markdown-alert-tip {border-left-color:var(--borderColor-success-emphasis, var(--color-success-emphasis));background-color:var(--color-success-subtle);}.markdown-alert.markdown-alert-tip .markdown-alert-title {color: var(--fgColor-success,var(--color-success-fg));}</style><style>.markdown-alert.markdown-alert-important {border-left-color:var(--borderColor-done-emphasis, var(--color-done-emphasis));background-color:var(--color-done-subtle);}.markdown-alert.markdown-alert-important .markdown-alert-title {color: var(--fgColor-done,var(--color-done-fg));}</style><style>.markdown-alert.markdown-alert-warning {border-left-color:var(--borderColor-attention-emphasis, var(--color-attention-emphasis));background-color:var(--color-attention-subtle);}.markdown-alert.markdown-alert-warning .markdown-alert-title {color: var(--fgColor-attention,var(--color-attention-fg));}</style>", "script": "", "head": "", "ogImage": "https://avatars.githubusercontent.com/u/161136026", "createdDate": "2024-09-28", "dateLabelColor": "#bc4c00"}}, "singeListJson": {}, "labelColorDict": {"\u6280\u672f\u8e29\u5751": "#CEA751", "\u65e5\u5e38": "#2E98F1"}, "displayTitle": "\u7fbd\u672b\u306e\u81ea\u7559\u5730", "faviconUrl": "https://avatars.githubusercontent.com/u/161136026", "ogImage": "https://avatars.githubusercontent.com/u/161136026", "primerCSS": "<link href='https://mirrors.sustech.edu.cn/cdnjs/ajax/libs/Primer/21.0.7/primer.css' rel='stylesheet' />", "homeUrl": "https://linmoyu233.github.io", "prevUrl": "disabled", "nextUrl": "disabled"}